<dataset type="EDDTableFromNcCFFiles" datasetID="11102sigs_burst-cal" active="true">
    <reloadEveryNMinutes>10080</reloadEveryNMinutes>
    
    <fileDir>/silt/usgs/Projects/stellwagen/CF-1.6/MATANZAS_18</fileDir>
    <fileNameRegex>11102sigs_burst-cal.nc</fileNameRegex>
    <recursive>true</recursive>
    <pathRegex>.*</pathRegex>
    <metadataFrom>last</metadataFrom>
    <preExtractRegex></preExtractRegex>
    <postExtractRegex></postExtractRegex>
    <extractRegex></extractRegex>
    <columnNameForExtract></columnNameForExtract>
    <sortFilesBySourceNames></sortFilesBySourceNames>
    <fileTableInMemory>false</fileTableInMemory>
    <accessibleViaFiles>true</accessibleViaFiles>
    <addAttributes>
        <att name="Conventions">CF-1.6,ACDD-1.3, COARDS</att>
        <att name="cdm_data_type">timeSeries</att>
        <att name="cdm_timeseries_variables">latitude, longitude, altitude, feature_type_instance</att>
        <att name="subsetVariables">latitude, longitude, altitude, feature_type_instance</att>
        <att name="infoUrl">https://stellwagen.er.usgs.gov/</att>
        <att name="keywords">feature_type_instance,latitude,longitude,crs,platform,time,z,AmbVel,Battery,sensor_depth,CD_310,CS_300,HSD_1218,Hdg_1215,PSD_1219,P_1,P_1ac,Ptch_1216,RSD_1220,Roll_1217,SV_80,Status,Sv_1232,TransMatrix,Tx_1211,Werr_1201,bindist,brange,burst,cor,error_bits,u_1205,v_1206,w_1204</att>
        <att name="license">[standard]</att>
        <att name="sourceUrl">(local files)</att>
        <att name="standard_name_vocabulary">CF Standard Name Table v29</att>
    </addAttributes>
    
    <dataVariable>
        <sourceName>feature_type_instance</sourceName>
        <destinationName>feature_type_instance</destinationName>
        <dataType>String</dataType>
        <addAttributes>
            
            <att name="ioos_category">Unknown</att>
            
        </addAttributes>
    </dataVariable>
    
    <dataVariable>
        <sourceName>latitude</sourceName>
        <destinationName>latitude</destinationName>
        <dataType>float</dataType>
        <addAttributes>
             
            <att name="colorBarMaximum" type="double">90.0</att>
            <att name="colorBarMinimum" type="double">-90.0</att>
            
            <att name="ioos_category">Location</att>
            
        </addAttributes>
    </dataVariable>
    
    <dataVariable>
        <sourceName>longitude</sourceName>
        <destinationName>longitude</destinationName>
        <dataType>float</dataType>
        <addAttributes>
             
            <att name="colorBarMaximum" type="double">180.0</att>
            <att name="colorBarMinimum" type="double">-180.0</att>
            
            <att name="ioos_category">Location</att>
            
        </addAttributes>
    </dataVariable>
    
    <dataVariable>
        <sourceName>crs</sourceName>
        <destinationName>crs</destinationName>
        <dataType>int</dataType>
        <addAttributes>
            
            <att name="ioos_category">Unknown</att>
            
        </addAttributes>
    </dataVariable>
    
    <dataVariable>
        <sourceName>platform</sourceName>
        <destinationName>platform</destinationName>
        <dataType>int</dataType>
        <addAttributes>
            
            <att name="ioos_category">Unknown</att>
            
        </addAttributes>
    </dataVariable>
    
    <dataVariable>
        <sourceName>time</sourceName>
        <destinationName>time</destinationName>
        <dataType>double</dataType>
        <addAttributes>
            
            <att name="ioos_category">Time</att>
            
        </addAttributes>
    </dataVariable>
    
    <dataVariable>
        <sourceName>z</sourceName>
        <destinationName>altitude</destinationName>
        <dataType>float</dataType>
        <addAttributes>
             
            <att name="colorBarMaximum" type="double">8000.0</att>
            <att name="colorBarMinimum" type="double">-8000.0</att>
            
            <att name="ioos_category">Location</att>
            
        </addAttributes>
    </dataVariable>
    
    <dataVariable>
        <sourceName>AmbVel</sourceName>
        <destinationName>AmbVel</destinationName>
        <dataType>float</dataType>
        <addAttributes>
             
            <att name="colorBarMaximum" type="double">1055.7621</att>
            <att name="colorBarMinimum" type="double">1038.0178</att>
            
            <att name="ioos_category">Unknown</att>
            
        </addAttributes>
    </dataVariable>
    
    <dataVariable>
        <sourceName>Battery</sourceName>
        <destinationName>Battery</destinationName>
        <dataType>float</dataType>
        <addAttributes>
             
            <att name="colorBarMaximum" type="double">18.701551</att>
            <att name="colorBarMinimum" type="double">18.699877</att>
            
            <att name="ioos_category">Unknown</att>
            
        </addAttributes>
    </dataVariable>
    
    <dataVariable>
        <sourceName>sensor_depth</sourceName>
        <destinationName>sensor_depth</destinationName>
        <dataType>double</dataType>
        <addAttributes>
            
            <att name="ioos_category">Unknown</att>
            
        </addAttributes>
    </dataVariable>
    
    <dataVariable>
        <sourceName>CD_310</sourceName>
        <destinationName>CD_310</destinationName>
        <dataType>float</dataType>
        <addAttributes>
             
            <att name="colorBarMaximum" type="double">359.97064</att>
            <att name="colorBarMinimum" type="double">0.0010392064</att>
            
            <att name="ioos_category">Unknown</att>
            
        </addAttributes>
    </dataVariable>
    
    <dataVariable>
        <sourceName>CS_300</sourceName>
        <destinationName>CS_300</destinationName>
        <dataType>float</dataType>
        <addAttributes>
             
            <att name="colorBarMaximum" type="double">0.50026923</att>
            <att name="colorBarMinimum" type="double">0.00027928245</att>
            
            <att name="ioos_category">Unknown</att>
            
        </addAttributes>
    </dataVariable>
    
    <dataVariable>
        <sourceName>HSD_1218</sourceName>
        <destinationName>HSD_1218</destinationName>
        <dataType>float</dataType>
        <addAttributes>
             
            <att name="colorBarMaximum" type="double">2.0520399</att>
            <att name="colorBarMinimum" type="double">0.07179162</att>
            
            <att name="ioos_category">Unknown</att>
            
        </addAttributes>
    </dataVariable>
    
    <dataVariable>
        <sourceName>Hdg_1215</sourceName>
        <destinationName>Hdg_1215</destinationName>
        <dataType>float</dataType>
        <addAttributes>
             
            <att name="colorBarMaximum" type="double">118.05287</att>
            <att name="colorBarMinimum" type="double">84.04394</att>
            
            <att name="ioos_category">Unknown</att>
            
        </addAttributes>
    </dataVariable>
    
    <dataVariable>
        <sourceName>PSD_1219</sourceName>
        <destinationName>PSD_1219</destinationName>
        <dataType>float</dataType>
        <addAttributes>
             
            <att name="colorBarMaximum" type="double">1.161586</att>
            <att name="colorBarMinimum" type="double">0.007886705</att>
            
            <att name="ioos_category">Unknown</att>
            
        </addAttributes>
    </dataVariable>
    
    <dataVariable>
        <sourceName>P_1</sourceName>
        <destinationName>P_1</destinationName>
        <dataType>float</dataType>
        <addAttributes>
             
            <att name="colorBarMaximum" type="double">9.0870075</att>
            <att name="colorBarMinimum" type="double">6.5396814</att>
            
            <att name="ioos_category">Unknown</att>
            
        </addAttributes>
    </dataVariable>
    
    <dataVariable>
        <sourceName>P_1ac</sourceName>
        <destinationName>P_1ac</destinationName>
        <dataType>float</dataType>
        <addAttributes>
             
            <att name="colorBarMaximum" type="double">8.836462</att>
            <att name="colorBarMinimum" type="double">6.33828</att>
            
            <att name="ioos_category">Unknown</att>
            
        </addAttributes>
    </dataVariable>
    
    <dataVariable>
        <sourceName>Ptch_1216</sourceName>
        <destinationName>Ptch_1216</destinationName>
        <dataType>float</dataType>
        <addAttributes>
             
            <att name="colorBarMaximum" type="double">1.1872063</att>
            <att name="colorBarMinimum" type="double">-1.5665286</att>
            
            <att name="ioos_category">Unknown</att>
            
        </addAttributes>
    </dataVariable>
    
    <dataVariable>
        <sourceName>RSD_1220</sourceName>
        <destinationName>RSD_1220</destinationName>
        <dataType>float</dataType>
        <addAttributes>
             
            <att name="colorBarMaximum" type="double">0.6568751</att>
            <att name="colorBarMinimum" type="double">0.007384083</att>
            
            <att name="ioos_category">Unknown</att>
            
        </addAttributes>
    </dataVariable>
    
    <dataVariable>
        <sourceName>Roll_1217</sourceName>
        <destinationName>Roll_1217</destinationName>
        <dataType>float</dataType>
        <addAttributes>
             
            <att name="colorBarMaximum" type="double">2.420551</att>
            <att name="colorBarMinimum" type="double">-0.82365817</att>
            
            <att name="ioos_category">Unknown</att>
            
        </addAttributes>
    </dataVariable>
    
    <dataVariable>
        <sourceName>SV_80</sourceName>
        <destinationName>SV_80</destinationName>
        <dataType>float</dataType>
        <addAttributes>
             
            <att name="colorBarMaximum" type="double">1520.2604</att>
            <att name="colorBarMinimum" type="double">1494.7162</att>
            
            <att name="ioos_category">Unknown</att>
            
        </addAttributes>
    </dataVariable>
    
    <dataVariable>
        <sourceName>Status</sourceName>
        <destinationName>Status</destinationName>
        <dataType>int</dataType>
        <addAttributes>
            
            <att name="ioos_category">Unknown</att>
            
        </addAttributes>
    </dataVariable>
    
    <dataVariable>
        <sourceName>Sv_1232</sourceName>
        <destinationName>Sv_1232</destinationName>
        <dataType>float</dataType>
        <addAttributes>
             
            <att name="colorBarMaximum" type="double">84.606964</att>
            <att name="colorBarMinimum" type="double">64.42093</att>
            
            <att name="ioos_category">Unknown</att>
            
        </addAttributes>
    </dataVariable>
    
    <dataVariable>
        <sourceName>TransMatrix</sourceName>
        <destinationName>TransMatrix</destinationName>
        <dataType>float</dataType>
        <addAttributes>
             
            <att name="colorBarMaximum" type="double">1.1831</att>
            <att name="colorBarMinimum" type="double">-1.1831</att>
            
            <att name="ioos_category">Unknown</att>
            
        </addAttributes>
    </dataVariable>
    
    <dataVariable>
        <sourceName>Tx_1211</sourceName>
        <destinationName>Tx_1211</destinationName>
        <dataType>float</dataType>
        <addAttributes>
             
            <att name="colorBarMaximum" type="double">19.525116</att>
            <att name="colorBarMinimum" type="double">11.335114</att>
            
            <att name="ioos_category">Unknown</att>
            
        </addAttributes>
    </dataVariable>
    
    <dataVariable>
        <sourceName>Werr_1201</sourceName>
        <destinationName>Werr_1201</destinationName>
        <dataType>float</dataType>
        <addAttributes>
             
            <att name="colorBarMaximum" type="double">25.888153</att>
            <att name="colorBarMinimum" type="double">-20.706133</att>
            
            <att name="ioos_category">Unknown</att>
            
        </addAttributes>
    </dataVariable>
    
    <dataVariable>
        <sourceName>bindist</sourceName>
        <destinationName>bindist</destinationName>
        <dataType>float</dataType>
        <addAttributes>
             
            <att name="colorBarMaximum" type="double">2.1</att>
            <att name="colorBarMinimum" type="double">0.3</att>
            
            <att name="ioos_category">Unknown</att>
            
        </addAttributes>
    </dataVariable>
    
    <dataVariable>
        <sourceName>brange</sourceName>
        <destinationName>brange</destinationName>
        <dataType>float</dataType>
        <addAttributes>
             
            <att name="colorBarMaximum" type="double">1.5040001</att>
            <att name="colorBarMinimum" type="double">1.2160001</att>
            
            <att name="ioos_category">Unknown</att>
            
        </addAttributes>
    </dataVariable>
    
    <dataVariable>
        <sourceName>burst</sourceName>
        <destinationName>burst</destinationName>
        <dataType>int</dataType>
        <addAttributes>
             
            <att name="colorBarMaximum" type="double">1895</att>
            <att name="colorBarMinimum" type="double">1</att>
            
            <att name="ioos_category">Unknown</att>
            
        </addAttributes>
    </dataVariable>
    
    <dataVariable>
        <sourceName>cor</sourceName>
        <destinationName>cor</destinationName>
        <dataType>float</dataType>
        <addAttributes>
             
            <att name="colorBarMaximum" type="double">98.079254</att>
            <att name="colorBarMinimum" type="double">43.70585</att>
            
            <att name="ioos_category">Unknown</att>
            
        </addAttributes>
    </dataVariable>
    
    <dataVariable>
        <sourceName>error_bits</sourceName>
        <destinationName>error_bits</destinationName>
        <dataType>short</dataType>
        <addAttributes>
            
            <att name="ioos_category">Unknown</att>
            
        </addAttributes>
    </dataVariable>
    
    <dataVariable>
        <sourceName>u_1205</sourceName>
        <destinationName>u_1205</destinationName>
        <dataType>float</dataType>
        <addAttributes>
             
            <att name="colorBarMaximum" type="double">0.29263395</att>
            <att name="colorBarMinimum" type="double">-0.12718795</att>
            
            <att name="ioos_category">Unknown</att>
            
        </addAttributes>
    </dataVariable>
    
    <dataVariable>
        <sourceName>v_1206</sourceName>
        <destinationName>v_1206</destinationName>
        <dataType>float</dataType>
        <addAttributes>
             
            <att name="colorBarMaximum" type="double">0.2675387</att>
            <att name="colorBarMinimum" type="double">-0.46420842</att>
            
            <att name="ioos_category">Unknown</att>
            
        </addAttributes>
    </dataVariable>
    
    <dataVariable>
        <sourceName>w_1204</sourceName>
        <destinationName>w_1204</destinationName>
        <dataType>float</dataType>
        <addAttributes>
             
            <att name="colorBarMaximum" type="double">0.034842607</att>
            <att name="colorBarMinimum" type="double">-0.14207423</att>
            
            <att name="ioos_category">Unknown</att>
            
        </addAttributes>
    </dataVariable>
    
</dataset>